SentinelAnomalyLookup/__init__.py
SentinelAnomalyLookup/anomaly_finder.py
SentinelAnomalyLookup/anomaly_lookup_view_helper.py
SentinelAzure/__init__.py
SentinelAzure/azure_loganalytics_helper.py
SentinelExceptions/__init__.py
SentinelExceptions/input_error.py
SentinelLog/__init__.py
SentinelLog/log.py
SentinelPortal/__init__.py
SentinelPortal/bookmark_helper.py
SentinelUtils/__init__.py
SentinelUtils/config_reader.py
SentinelUtils/input_validation.py
SentinelUtils/obfuscation_utility.py
SentinelUtils/version_management.py
SentinelWidgets/__init__.py
SentinelWidgets/widget_view_helper.py
Azure_Sentinel_Utilities-0.6.5.dist-info/LICENSE.txt
Azure_Sentinel_Utilities-0.6.5.dist-info/METADATA
Azure_Sentinel_Utilities-0.6.5.dist-info/WHEEL
Azure_Sentinel_Utilities-0.6.5.dist-info/top_level.txt
Azure_Sentinel_Utilities-0.6.5.dist-info/RECORD
