Metadata-Version: 2.1
Name: Azure-Sentinel-Utilities
Version: 0.6.5
Summary: AZURE SENTINEL NOTEBOOKS PYTHON TOOLS:     This package is developed to support Azure Sentinel Notebooks.      It is in an early preview stage so please provide feedback,     report bugs, and suggets for new features.
Home-page: https://github.com/Azure/Azure-Sentinel
Author: Azure Sentinel Notebooks Devs
Author-email: zhzhao@microsoft.com
License: Azure-Sentinel-Utilities Copyright (c) Microsoft Corporation. All rights reserved.
Requires-Dist: azure-loganalytics (>=0.1.0)
Requires-Dist: azure-mgmt-loganalytics (>=0.2.0)
Requires-Dist: azure-common (>=1.1.25)
Requires-Dist: azure-cli-core (>=2.7.0)
